src/__init__.py
src/cli.py
src/database.py
src/server.py
src/common/browser_use_common.py
src/handlers/__init__.py
src/handlers/persona_runner.py
src/handlers/persona_runs.py
src/handlers/reports.py
src/handlers/scenarios.py
src/handlers/system_config.py
src/handlers/task_generation.py
src/models/__init__.py
src/models/common.py
src/models/crawler_run.py
src/models/persona_run.py
src/models/scenario.py
src/models/schemas.py
src/models/system_config.py
src/prompts/task_generator_prompt.txt
src/prompts/user_journey_task.txt
src/prompts/website_crawler_prompt.txt
src/routers/__init__.py
src/routers/persona_runner.py
src/routers/persona_runs.py
src/routers/reports.py
src/routers/scenarios.py
src/routers/system_config.py
src/static/404.html
src/static/__next.__PAGE__.txt
src/static/__next._full.txt
src/static/__next._index.txt
src/static/__next._tree.txt
src/static/apple-icon.png
src/static/favicon.png
src/static/index.html
src/static/index.txt
src/static/usefly-logo.png
src/static/404/index.html
src/static/_next/static/VHmwfiZfv2BbfJVaqgI0Z/_buildManifest.js
src/static/_next/static/VHmwfiZfv2BbfJVaqgI0Z/_clientMiddlewareManifest.json
src/static/_next/static/VHmwfiZfv2BbfJVaqgI0Z/_ssgManifest.js
src/static/_next/static/chunks/05f78a5217bc8630.js
src/static/_next/static/chunks/0eabd4a07300acc6.js
src/static/_next/static/chunks/10f6e7c27ee20315.js
src/static/_next/static/chunks/1e109efa3fe1594f.js
src/static/_next/static/chunks/2810242f8bf4ae1d.js
src/static/_next/static/chunks/3105d6d8e5720a3e.js
src/static/_next/static/chunks/39196b75e316ff16.js
src/static/_next/static/chunks/3cdf177b8b521e01.css
src/static/_next/static/chunks/42d7898b2e3d1c94.js
src/static/_next/static/chunks/4b0d58d8b18dc988.js
src/static/_next/static/chunks/501d3bc7f32acf69.js
src/static/_next/static/chunks/54f22b0d9a3d333c.js
src/static/_next/static/chunks/5d5e03acf2f3037a.js
src/static/_next/static/chunks/5d7d4abab63d3a9f.js
src/static/_next/static/chunks/61239e1574a77c0e.js
usefly-0.1.6.dist-info/licenses/LICENSE
usefly-0.1.6.dist-info/METADATA
usefly-0.1.6.dist-info/WHEEL
usefly-0.1.6.dist-info/entry_points.txt
usefly-0.1.6.dist-info/top_level.txt
usefly-0.1.6.dist-info/RECORD
