Metadata-Version: 2.4
Name: usefly
Version: 0.1.6
Summary: Agentic UX Analytics - Test your app with AI agents
Author: Usefly Team
License: MIT
Keywords: ux,analytics,ai,agents,testing,automation
Classifier: Development Status :: 3 - Alpha
Classifier: Intended Audience :: Developers
Classifier: License :: OSI Approved :: MIT License
Classifier: Programming Language :: Python :: 3
Classifier: Programming Language :: Python :: 3.12
Requires-Python: >=3.12
License-File: LICENSE
Requires-Dist: fastapi>=0.104.0
Requires-Dist: uvicorn[standard]>=0.24.0
Requires-Dist: sqlalchemy>=2.0.0
Requires-Dist: pydantic>=2.0.0
Requires-Dist: click>=8.1.0
Requires-Dist: browser-use>=0.10.1
Requires-Dist: python-dotenv==1.0.1
Requires-Dist: pillow>=10.0.0
Requires-Dist: imageio[ffmpeg]>=2.34.0
Requires-Dist: langchain>=1.0.7
Requires-Dist: langchain-openai>=1.0.3
Requires-Dist: langchain-core>=1.0.5
Requires-Dist: langchain-anthropic>=1.2.0
Provides-Extra: dev
Requires-Dist: pytest>=7.0.0; extra == "dev"
Requires-Dist: pytest-asyncio>=0.23.0; extra == "dev"
Requires-Dist: ruff>=0.1.0; extra == "dev"
Dynamic: license-file
